configparse/__init__.py
configparse/core.py
configparse/backends/__init__.py
configparse/backends/ini.py
configparse/backends/json.py
configparse/backends/toml.py
configparse/backends/yaml.py
configparse-0.1.5.dist-info/LICENSE
configparse-0.1.5.dist-info/METADATA
configparse-0.1.5.dist-info/WHEEL
configparse-0.1.5.dist-info/top_level.txt
configparse-0.1.5.dist-info/RECORD
