Metadata-Version: 2.1
Name: configparse
Version: 0.1.5
Summary: Drop-in substitute for argparse that reads config files
Home-page: https://github.com/jyn514/configparse/
Author: Joshua Nelson
Author-email: jyn514@gmail.com
License: BSD
Keywords: configuration,argparse
Platform: UNKNOWN
Classifier: Development Status :: 2 - Pre-Alpha
Classifier: Environment :: Console
Classifier: Intended Audience :: End Users/Desktop
Classifier: Intended Audience :: Developers
Classifier: Intended Audience :: System Administrators
Classifier: Programming Language :: Python :: 3
Classifier: License :: OSI Approved :: MIT License
Classifier: Operating System :: OS Independent
Classifier: Topic :: Software Development :: Libraries
Provides-Extra: toml
Provides-Extra: yaml
